Metadata-Version: 2.1
Name: FtoC
Version: 0.0.3
Summary: Converts temperatures from farenheit to celsius.
Home-page: https://github.com/abhinav-gg/StupidPipPackages/FtoC
Author: Abhinav G
Author-email: agupta.cam7@gmail.com
License: MIT
Keywords: faren,farenheit,temp,temperature,degrees,degrees c,degrees f,celsius,c,f,ftoc
Platform: UNKNOWN
Classifier: Programming Language :: Python :: 3
Classifier: License :: OSI Approved :: MIT License
Classifier: Operating System :: OS Independent
